dmessage/__init__.py
dmessage/dmessage.py
dmessage-0.2.1.dist-info/LICENSE
dmessage-0.2.1.dist-info/METADATA
dmessage-0.2.1.dist-info/WHEEL
dmessage-0.2.1.dist-info/RECORD
